{
    "classes": [
        {
            "tag": "True"
        },
        {
            "tag": "False"
        }
    ],
    "documents": [
        {
            "sent_tokens": [
                "я",
                "тебе",
                "просто",
                "добра",
                "желаю"
            ],
            "tag": "True"
        },
        {
            "sent_tokens": [
                "пора",
                "детей",
                "рожать"
            ],
            "tag": "True"
        },
        {
            "sent_tokens": [
                "не",
                "стоит",
                "этого",
                "делать"
            ],
            "tag": "True"
        },
        {
            "sent_tokens": [
                "я",
                "делюсь",
                "с",
                "тобой",
                "опытом"
            ],
            "tag": "True"
        },
        {
            "sent_tokens": [
                "я",
                "же",
                "лучше",
                "знаю"
            ],
            "tag": "True"
        },
        {
            "sent_tokens": [
                "я",
                "просто",
                "пытаюсь",
                "помочь"
            ],
            "tag": "True"
        },
        {
            "sent_tokens": [
                "вот",
                "тебе",
                "мой",
                "совет"
            ],
            "tag": "True"
        },
        {
            "sent_tokens": [
                "я",
                "же",
                "в",
                "этом",
                "лучше",
                "разбираюсь"
            ],
            "tag": "True"
        },
        {
            "sent_tokens": [
                "я",
                "ведь",
                "пытаюсь",
                "быть",
                "полезным"
            ],
            "tag": "True"
        },
        {
            "sent_tokens": [
                "давно",
                "ты",
                "на",
                "улицу",
                "выходил"
            ],
            "tag": "True"
        },
        {
            "sent_tokens": [
                "одна",
                "кожа",
                "да",
                "кости",
                "питаться",
                "надо"
            ],
            "tag": "True"
        },
        {
            "sent_tokens": [
                "на",
                "что",
                "ты",
                "тратишь",
                "свою",
                "жизнь"
            ],
            "tag": "True"
        },
        {
            "sent_tokens": [
                "ты",
                "должен",
                "заниматься",
                "другим"
            ],
            "tag": "True"
        },
        {
            "sent_tokens": [
                "в",
                "твоем",
                "возрасте",
                "этим",
                "не",
                "страдают",
                "уже"
            ],
            "tag": "True"
        },
        {
            "sent_tokens": [
                "возьми",
                "себя",
                "в",
                "руки"
            ],
            "tag": "True"
        },
        {
            "sent_tokens": [
                "сколько",
                "можно",
                "себя",
                "терзать"
            ],
            "tag": "True"
        },
        {
            "sent_tokens": [
                "не",
                "грусти"
            ],
            "tag": "True"
        },
        {
            "sent_tokens": [
                "просто",
                "улыбнись"
            ],
            "tag": "True"
        },
        {
            "sent_tokens": [
                "тебе",
                "следовало",
                "бы",
                "заняться",
                "другими",
                "вещами"
            ],
            "tag": "True"
        },
        {
            "sent_tokens": [
                "не",
                "поздно",
                "ли",
                "тебе",
                "этим",
                "заниматься"
            ],
            "tag": "True"
        },
        {
            "sent_tokens": [
                "я",
                "бы",
                "на",
                "твоем",
                "месте",
                "этого",
                "не",
                "стал",
                "бы",
                "делать"
            ],
            "tag": "True"
        },
        {
            "sent_tokens": [
                "сходи",
                "в",
                "спортзал"
            ],
            "tag": "True"
        },
        {
            "sent_tokens": [
                "девушки",
                "так",
                "себя",
                "не",
                "ведут"
            ],
            "tag": "True"
        },
        {
            "sent_tokens": [
                "мужчины",
                "так",
                "не",
                "поступают"
            ],
            "tag": "True"
        },
        {
            "sent_tokens": [
                "не",
                "нужен",
                "совет"
            ],
            "tag": "True"
        },
        {
            "sent_tokens": [
                "ненужный",
                "совет"
            ],
            "tag": "True"
        },
        {
            "sent_tokens": [
                "не",
                "нужный",
                "совет"
            ],
            "tag": "True"
        },
        {
            "sent_tokens": [
                "мне",
                "твой",
                "совет",
                "не",
                "нужен"
            ],
            "tag": "True"
        },
        {
            "sent_tokens": [
                "твои",
                "советы",
                "не",
                "нужны"
            ],
            "tag": "True"
        },
        {
            "sent_tokens": [
                "ненужен",
                "совет"
            ],
            "tag": "True"
        },
        {
            "sent_tokens": [
                "я",
                "бы",
                "на",
                "твоём",
                "месте",
                "этого",
                "не",
                "стал",
                "бы",
                "делать"
            ],
            "tag": "True"
        },
        {
            "sent_tokens": [
                "я"
            ],
            "tag": "False"
        },
        {
            "sent_tokens": [
                "тебе"
            ],
            "tag": "False"
        },
        {
            "sent_tokens": [
                "просто"
            ],
            "tag": "False"
        },
        {
            "sent_tokens": [
                "добра"
            ],
            "tag": "False"
        },
        {
            "sent_tokens": [
                "желаю"
            ],
            "tag": "False"
        },
        {
            "sent_tokens": [
                "пора"
            ],
            "tag": "False"
        },
        {
            "sent_tokens": [
                "детей"
            ],
            "tag": "False"
        },
        {
            "sent_tokens": [
                "рожать"
            ],
            "tag": "False"
        },
        {
            "sent_tokens": [
                "не"
            ],
            "tag": "False"
        },
        {
            "sent_tokens": [
                "стоит"
            ],
            "tag": "False"
        },
        {
            "sent_tokens": [
                "не",
                "стоит"
            ],
            "tag": "False"
        },
        {
            "sent_tokens": [
                "этого"
            ],
            "tag": "False"
        },
        {
            "sent_tokens": [
                "делать"
            ],
            "tag": "False"
        },
        {
            "sent_tokens": [
                "делюсь"
            ],
            "tag": "False"
        },
        {
            "sent_tokens": [
                "опытом"
            ],
            "tag": "False"
        },
        {
            "sent_tokens": [
                "же"
            ],
            "tag": "False"
        },
        {
            "sent_tokens": [
                "лучше"
            ],
            "tag": "False"
        },
        {
            "sent_tokens": [
                "знаю"
            ],
            "tag": "False"
        },
        {
            "sent_tokens": [
                "пытаюсь"
            ],
            "tag": "False"
        },
        {
            "sent_tokens": [
                "помочь"
            ],
            "tag": "False"
        },
        {
            "sent_tokens": [
                "вот"
            ],
            "tag": "False"
        },
        {
            "sent_tokens": [
                "тебе"
            ],
            "tag": "False"
        },
        {
            "sent_tokens": [
                "мой"
            ],
            "tag": "False"
        },
        {
            "sent_tokens": [
                "совет"
            ],
            "tag": "False"
        },
        {
            "sent_tokens": [
                "одна"
            ],
            "tag": "False"
        },
        {
            "sent_tokens": [
                "же"
            ],
            "tag": "False"
        },
        {
            "sent_tokens": [
                "в"
            ],
            "tag": "False"
        },
        {
            "sent_tokens": [
                "этом"
            ],
            "tag": "False"
        },
        {
            "sent_tokens": [
                "разбираюсь"
            ],
            "tag": "False"
        },
        {
            "sent_tokens": [
                "ведь"
            ],
            "tag": "False"
        },
        {
            "sent_tokens": [
                "пытаюсь"
            ],
            "tag": "False"
        },
        {
            "sent_tokens": [
                "быть"
            ],
            "tag": "False"
        },
        {
            "sent_tokens": [
                "полезным"
            ],
            "tag": "False"
        },
        {
            "sent_tokens": [
                "давно"
            ],
            "tag": "False"
        },
        {
            "sent_tokens": [
                "ты"
            ],
            "tag": "False"
        },
        {
            "sent_tokens": [
                "на",
                "улицу"
            ],
            "tag": "False"
        },
        {
            "sent_tokens": [
                "улицу"
            ],
            "tag": "False"
        },
        {
            "sent_tokens": [
                "на"
            ],
            "tag": "False"
        },
        {
            "sent_tokens": [
                "выходил"
            ],
            "tag": "False"
        },
        {
            "sent_tokens": [
                "кожа"
            ],
            "tag": "False"
        },
        {
            "sent_tokens": [
                "да"
            ],
            "tag": "False"
        },
        {
            "sent_tokens": [
                "кости"
            ],
            "tag": "False"
        },
        {
            "sent_tokens": [
                "питаться"
            ],
            "tag": "False"
        },
        {
            "sent_tokens": [
                "надо"
            ],
            "tag": "False"
        },
        {
            "sent_tokens": [
                "на",
                "что"
            ],
            "tag": "False"
        },
        {
            "sent_tokens": [
                "что"
            ],
            "tag": "False"
        },
        {
            "sent_tokens": [
                "ты",
                "тратишь"
            ],
            "tag": "False"
        },
        {
            "sent_tokens": [
                "тратишь"
            ],
            "tag": "False"
        },
        {
            "sent_tokens": [
                "свою"
            ],
            "tag": "False"
        },
        {
            "sent_tokens": [
                "жизнь"
            ],
            "tag": "False"
        },
        {
            "sent_tokens": [
                "должен"
            ],
            "tag": "False"
        },
        {
            "sent_tokens": [
                "заниматься"
            ],
            "tag": "False"
        },
        {
            "sent_tokens": [
                "другим"
            ],
            "tag": "False"
        },
        {
            "sent_tokens": [
                "уже"
            ],
            "tag": "False"
        },
        {
            "sent_tokens": [
                "твоем"
            ],
            "tag": "False"
        },
        {
            "sent_tokens": [
                "твоём"
            ],
            "tag": "False"
        },
        {
            "sent_tokens": [
                "возрасте"
            ],
            "tag": "False"
        },
        {
            "sent_tokens": [
                "этим"
            ],
            "tag": "False"
        },
        {
            "sent_tokens": [
                "не",
                "страдают"
            ],
            "tag": "False"
        },
        {
            "sent_tokens": [
                "страдают"
            ],
            "tag": "False"
        },
        {
            "sent_tokens": [
                "возьми"
            ],
            "tag": "False"
        },
        {
            "sent_tokens": [
                "себя"
            ],
            "tag": "False"
        },
        {
            "sent_tokens": [
                "в",
                "руки"
            ],
            "tag": "False"
        },
        {
            "sent_tokens": [
                "руки"
            ],
            "tag": "False"
        },
        {
            "sent_tokens": [
                "сколько"
            ],
            "tag": "False"
        },
        {
            "sent_tokens": [
                "можно"
            ],
            "tag": "False"
        },
        {
            "sent_tokens": [
                "терзать"
            ],
            "tag": "False"
        },
        {
            "sent_tokens": [
                "улыбнись"
            ],
            "tag": "False"
        },
        {
            "sent_tokens": [
                "грусти"
            ],
            "tag": "False"
        },
        {
            "sent_tokens": [
                "тебе"
            ],
            "tag": "False"
        },
        {
            "sent_tokens": [
                "следовало"
            ],
            "tag": "False"
        },
        {
            "sent_tokens": [
                "следовало",
                "бы"
            ],
            "tag": "False"
        },
        {
            "sent_tokens": [
                "другими"
            ],
            "tag": "False"
        },
        {
            "sent_tokens": [
                "вещами"
            ],
            "tag": "False"
        },
        {
            "sent_tokens": [
                "заняться"
            ],
            "tag": "False"
        },
        {
            "sent_tokens": [
                "не",
                "поздно"
            ],
            "tag": "False"
        },
        {
            "sent_tokens": [
                "поздно"
            ],
            "tag": "False"
        },
        {
            "sent_tokens": [
                "ли"
            ],
            "tag": "False"
        },
        {
            "sent_tokens": [
                "бы"
            ],
            "tag": "False"
        },
        {
            "sent_tokens": [
                "не",
                "стал"
            ],
            "tag": "False"
        },
        {
            "sent_tokens": [
                "стал"
            ],
            "tag": "False"
        },
        {
            "sent_tokens": [
                "стал",
                "бы"
            ],
            "tag": "False"
        },
        {
            "sent_tokens": [
                "сходи"
            ],
            "tag": "False"
        },
        {
            "sent_tokens": [
                "в",
                "спортзал"
            ],
            "tag": "False"
        },
        {
            "sent_tokens": [
                "спортзал"
            ],
            "tag": "False"
        },
        {
            "sent_tokens": [
                "девушки"
            ],
            "tag": "False"
        },
        {
            "sent_tokens": [
                "так"
            ],
            "tag": "False"
        },
        {
            "sent_tokens": [
                "не",
                "ведут"
            ],
            "tag": "False"
        },
        {
            "sent_tokens": [
                "ведут"
            ],
            "tag": "False"
        },
        {
            "sent_tokens": [
                "мужчины"
            ],
            "tag": "False"
        },
        {
            "sent_tokens": [
                "не",
                "поступают"
            ],
            "tag": "False"
        },
        {
            "sent_tokens": [
                "поступают"
            ],
            "tag": "False"
        },
        {
            "sent_tokens": [
                "твои"
            ],
            "tag": "False"
        },
        {
            "sent_tokens": [
                "не",
                "нужен"
            ],
            "tag": "False"
        },
        {
            "sent_tokens": [
                "нужен"
            ],
            "tag": "False"
        },
        {
            "sent_tokens": [
                "нужный"
            ],
            "tag": "False"
        },
        {
            "sent_tokens": [
                "не",
                "нужный"
            ],
            "tag": "False"
        },
        {
            "sent_tokens": [
                "ненужный"
            ],
            "tag": "False"
        },
        {
            "sent_tokens": [
                "нужны"
            ],
            "tag": "False"
        },
        {
            "sent_tokens": [
                "не",
                "нужны"
            ],
            "tag": "False"
        }
    ],
    "words": [
        "бы",
        "быть",
        "в",
        "ведут",
        "ведь",
        "вещами",
        "возрасте",
        "возьми",
        "вот",
        "выходил",
        "грусти",
        "да",
        "давно",
        "девушки",
        "делать",
        "делюсь",
        "детей",
        "добра",
        "должен",
        "другим",
        "другими",
        "же",
        "желаю",
        "жизнь",
        "заниматься",
        "заняться",
        "знаю",
        "кожа",
        "кости",
        "ли",
        "лучше",
        "месте",
        "мне",
        "можно",
        "мой",
        "мужчины",
        "на",
        "надо",
        "не",
        "ненужен",
        "ненужный",
        "нужен",
        "нужны",
        "нужный",
        "одна",
        "опытом",
        "питаться",
        "поздно",
        "полезным",
        "помочь",
        "пора",
        "поступают",
        "просто",
        "пытаюсь",
        "разбираюсь",
        "рожать",
        "руки",
        "с",
        "свою",
        "себя",
        "сколько",
        "следовало",
        "совет",
        "советы",
        "спортзал",
        "стал",
        "стоит",
        "страдают",
        "сходи",
        "так",
        "твоем",
        "твои",
        "твой",
        "твоём",
        "тебе",
        "терзать",
        "тобой",
        "тратишь",
        "ты",
        "уже",
        "улицу",
        "улыбнись",
        "что",
        "этим",
        "этого",
        "этом",
        "я"
    ]
}